setup.py
koel/__init__.py
koel.egg-info/PKG-INFO
koel.egg-info/SOURCES.txt
koel.egg-info/dependency_links.txt
koel.egg-info/not-zip-safe
koel.egg-info/top_level.txt