Metadata-Version: 1.0
Name: koel
Version: 0.1
Summary: General scraping framework
Home-page: http://github.com/whoiscc/koel
Author: whoiscc
Author-email: correctizer@gmail.com
License: MIT
Platform: UNKNOWN
